sphinx_blue_robotics_theme/__init__.py
sphinx_blue_robotics_theme/_version.py
sphinx_blue_robotics_theme/base.html
sphinx_blue_robotics_theme/drawer.json
sphinx_blue_robotics_theme/extensions/cpp.py
sphinx_blue_robotics_theme/extensions/extras.py
sphinx_blue_robotics_theme/extensions/hero.py
sphinx_blue_robotics_theme/extensions/lua.py
sphinx_blue_robotics_theme/extensions/multiversion.py
sphinx_blue_robotics_theme/extensions/python.py
sphinx_blue_robotics_theme/partials/content.html
sphinx_blue_robotics_theme/partials/copyright.html
sphinx_blue_robotics_theme/partials/footer.html
sphinx_blue_robotics_theme/partials/header.html
sphinx_blue_robotics_theme/partials/icon.html
sphinx_blue_robotics_theme/partials/logo.html
sphinx_blue_robotics_theme/partials/megamenu.html
sphinx_blue_robotics_theme/partials/nav.html
sphinx_blue_robotics_theme/partials/rightdrawer.html
sphinx_blue_robotics_theme/partials/versions.html
sphinx_blue_robotics_theme/static/.DS_Store
sphinx_blue_robotics_theme/static/css/main.css
sphinx_blue_robotics_theme/static/favicon.ico
sphinx_blue_robotics_theme/static/fonts/Windsor-BOLD.ttf
sphinx_blue_robotics_theme/static/img/bg.jpg
sphinx_blue_robotics_theme/static/img/icon.png
sphinx_blue_robotics_theme/static/img/logo-dark.png
sphinx_blue_robotics_theme/static/img/logo.png
sphinx_blue_robotics_theme/static/js/jquery.min.js
sphinx_blue_robotics_theme/static/js/main.js
sphinx_blue_robotics_theme/theme.conf
sphinx_blue_robotics_theme/utils.py
sphinx_blue_robotics_theme-0.0.3.dist-info/LICENSE
sphinx_blue_robotics_theme-0.0.3.dist-info/METADATA
sphinx_blue_robotics_theme-0.0.3.dist-info/WHEEL
sphinx_blue_robotics_theme-0.0.3.dist-info/RECORD
