Metadata-Version: 2.1
Name: sphinx-blue-robotics-theme
Version: 0.0.3
Summary: Sphinx theme for BlueRobotics documentation projects
Author: TechDocs Studio
Author-email: info@techdocs.studio
Requires-Python: >=3.10,<4.0
Classifier: Programming Language :: Python :: 3
Classifier: Programming Language :: Python :: 3.10
Classifier: Programming Language :: Python :: 3.11
Classifier: Programming Language :: Python :: 3.12
Classifier: Programming Language :: Python :: 3.13
Provides-Extra: cpp
Provides-Extra: extras
Provides-Extra: lua
Provides-Extra: python
Requires-Dist: breathe (>=4.35.0) ; extra == "cpp"
Requires-Dist: exhale (>=0.3.7) ; extra == "cpp"
Requires-Dist: myst-parser (>=4.0.0,<5.0.0)
Requires-Dist: sphinx-autodoc2 (>=0.5.0) ; extra == "python"
Requires-Dist: sphinx-design (>=0.6.1,<0.7.0) ; extra == "extras"
Requires-Dist: sphinx-immaterial (>=0.12.4,<0.13.0)
Requires-Dist: sphinx-lua (>=1.1.5) ; extra == "lua"
